pylutron/__init__.py
pylutron_koreth/__init__.py
pylutron_koreth-0.1.2.dist-info/DESCRIPTION.rst
pylutron_koreth-0.1.2.dist-info/METADATA
pylutron_koreth-0.1.2.dist-info/RECORD
pylutron_koreth-0.1.2.dist-info/WHEEL
pylutron_koreth-0.1.2.dist-info/metadata.json
pylutron_koreth-0.1.2.dist-info/top_level.txt
pylutron_koreth-0.1.2.dist-info/zip-safe
